Metadata-Version: 1.0
Name: strict-shuffle-array
Version: 0.0
Summary: Shuffles the array so that any element takes a new place
Home-page: UNKNOWN
Author: Cringe_code
Author-email: bibikonfikus1234@gmail.com
License: UNKNOWN
Platform: UNKNOWN
